{"token_type": "Bearer", "expires_at": 1606669515, "expires_in": 18846, "refresh_token": "7533c08ca583fd004e8a1e3a3592381acccc2b1d", "access_token": "fb4346c7a647b8a782a46fc4292a1680c848f115", "athlete": {"id": 5836753, "username": "ddolic", "resource_state": 2, "firstname": "Dubravko", "lastname": "Dolic", "city": "Rosenheim", "state": "Bayern", "country": "Deutschland", "sex": "M", "premium": true, "summit": true, "created_at": "2014-07-29T12:02:10Z", "updated_at": "2020-11-29T11:05:15Z", "badge_type_id": 1, "profile_medium": "https://dgalywyr863hv.cloudfront.net/pictures/athletes/5836753/1807882/2/medium.jpg", "profile": "https://dgalywyr863hv.cloudfront.net/pictures/athletes/5836753/1807882/2/large.jpg", "friend": null, "follower": null}}